consoledev/__init__.py
consoledev/__main__.py
consoledev/consolekit.py
consoledev-1.0.4.dist-info/METADATA
consoledev-1.0.4.dist-info/WHEEL
consoledev-1.0.4.dist-info/entry_points.txt
consoledev-1.0.4.dist-info/top_level.txt
consoledev-1.0.4.dist-info/RECORD
