Metadata-Version: 2.1
Name: consoledev
Version: 1.0.4
Summary: Light tool for creating interactive colored consoles.
Home-page: https://github.com/jonaprojects/consoledev
Author: Jonathan
Author-email: jojona1357@gmail.com
License: MIT
Platform: UNKNOWN
Classifier: License :: OSI Approved :: MIT License
Classifier: Programming Language :: Python :: 3
Classifier: Programming Language :: Python :: 3.7
